data_stream/data_stream.v
module data_stream(
    input wire clk,
    input wire rst,
    output reg data_out
);

reg [7:0] counter;

always @(posedge clk or posedge rst) begin
    if (rst) begin
        counter <= 8'b0;
        data_out <= 0;
    end else begin
        counter <= counter + 1;
        data_out <= counter[0];  // Simple data stream using LSB of counter
    end
end

endmodule

data_stream/data_stream_tb.v
`timescale 1ns/1ps

module testbench;

reg clk;
reg rst;
wire data_out;

// Instantiate the data_stream module
data_stream uut (
    .clk(clk),
    .rst(rst),
    .data_out(data_out)
);

// Clock generation
initial begin
    clk = 0;
    forever #5 clk = ~clk; // 100MHz clock
end

// Test sequence
initial begin
    // Open VCD file for dumping
    $dumpfile("data_stream.vcd");
    $dumpvars(0, testbench);

    // Initialize
    rst = 1;
    #10;

    // Release reset
    rst = 0;

    // Run simulation for 200ns
    #200;

    // End simulation
    $finish;
end

endmodule

data_stream/data_stream.vcd
$date
	Fri Jun 21 12:25:03 2024
$end
$version
	Icarus Verilog
$end
$timescale
	1ps
$end
$scope module testbench $end
$var reg 1 ! clk $end
$upscope $end
$scope module testbench $end
$var reg 1 " rst $end
$upscope $end
$scope module testbench $end
$var wire 1 # data_out $end
$upscope $end
$enddefinitions $end
#0
$dumpvars
0#
1"
0!
$end
#5000
1!
#10000
0!
0"
#15000
1!
#20000
0!
#25000
1#
1!
#30000
0!
#35000
0#
1!
#40000
0!
#45000
1#
1!
#50000
0!
#55000
0#
1!
#60000
0!
#65000
1#
1!
#70000
0!
#75000
0#
1!
#80000
0!
#85000
1#
1!
#90000
0!
#95000
0#
1!
#100000
0!
#105000
1#
1!
#110000
0!
#115000
0#
1!
#120000
0!
#125000
1#
1!
#130000
0!
#135000
0#
1!
#140000
0!
#145000
1#
1!
#150000
0!
#155000
0#
1!
#160000
0!
#165000
1#
1!
#170000
0!
#175000
0#
1!
#180000
0!
#185000
1#
1!
#190000
0!
#195000
0#
1!
#200000
0!
#205000
1#
1!
